tdnss/__init__.py
tdnss/baseresponse.py
tdnss/config.py
tdnss/connection.py
tdnss/customformatter.py
tdnss/settings_api.py
tdnss/zone_api.py
tdnss-0.2.1.dist-info/METADATA
tdnss-0.2.1.dist-info/WHEEL
tdnss-0.2.1.dist-info/licenses/COPYING
tdnss-0.2.1.dist-info/RECORD
