Metadata-Version: 2.1
Name: tdnss
Version: 0.2.1
Summary: A Python wrapper of Technitium DNS server's API
Project-URL: Homepage, https://codeberg.org/JulioLoayzaM/tdnss
Project-URL: Bug Tracker, https://codeberg.org/JulioLoayzaM/tdnss/issues
Author-email: Julio Loayza Meneses <julio+tdnss@loayzameneses.com>, Chris Edstrom <cedstrom+tdnss@outlook.com>
License-File: COPYING
Classifier: License :: OSI Approved :: GNU General Public License v3 (GPLv3)
Classifier: Operating System :: OS Independent
Classifier: Programming Language :: Python :: 3
Requires-Python: >=3.7
Requires-Dist: requests==2.31.0
Requires-Dist: strenum==0.4.15
